LICENSE
th2_act_core/__init__.py
th2_act_core/act.py
th2_act_core/act_message.py
th2_act_core/act_server.py
th2_act_core/grpc_method_attributes.py
th2_act_core/handler_attributes.py
th2_act_core/request_processor.py
th2_act_core/util/__init__.py
th2_act_core/util/act_events.py
th2_act_core/util/act_receiver.py
th2_act_core/util/act_sender.py
th2_act_core/util/cache.py
th2_act_core/util/cache_filter.py
th2_act_core/util/grpc_context_manager.py
th2_act_core/util/subscription_manager.py
th2_act_core-1.0.0.dist-info/LICENSE
th2_act_core-1.0.0.dist-info/WHEEL
th2_act_core-1.0.0.dist-info/METADATA
th2_act_core-1.0.0.dist-info/RECORD
